bemyeyes_django_cte/__init__.py
bemyeyes_django_cte/cte.py
bemyeyes_django_cte/expressions.py
bemyeyes_django_cte/join.py
bemyeyes_django_cte/meta.py
bemyeyes_django_cte/query.py
bemyeyes_django_cte/raw.py
bemyeyes_django_cte-1.3.4.dist-info/licenses/LICENSE
bemyeyes_django_cte-1.3.4.dist-info/WHEEL
bemyeyes_django_cte-1.3.4.dist-info/METADATA
bemyeyes_django_cte-1.3.4.dist-info/RECORD
